uatrack/__init__.py
uatrack/assignment.py
uatrack/core.py
uatrack/filter.py
uatrack/metrics.py
uatrack/models.py
uatrack/output.py
uatrack/sampling.py
uatrack/utils.py
uatrack/config/__init__.py
uatrack/solve/__init__.py
uatrack/solve/gurobi.py
uatrack/solve/mip.py
uatrack-0.0.5.dist-info/METADATA
uatrack-0.0.5.dist-info/WHEEL
uatrack-0.0.5.dist-info/entry_points.txt
uatrack-0.0.5.dist-info/top_level.txt
uatrack-0.0.5.dist-info/RECORD
