Metadata-Version: 2.1
Name: uatrack
Version: 0.0.5
Summary: Uncertainty-Aware Tracking Framework.
Home-page: https://github.com/JuBiotech/PyUAT
Author: Johannes Seiffarth
Author-email: j.seiffarth@fz-juelich.de
License: MIT license
Keywords: uatrack
Platform: UNKNOWN
Requires-Python: >=3.6
Requires-Dist: acia==0.2.37
Requires-Dist: tensor-walks==0.0.7
Requires-Dist: mip>=1.15.0
Requires-Dist: ray
Requires-Dist: gurobipy==9.5.2
Provides-Extra: gurobi
Requires-Dist: gurobipy>=5.9.3; extra == "gurobi"
Provides-Extra: test
Requires-Dist: pytest>=3; extra == "test"
Requires-Dist: wget; extra == "test"
